confixer/__init__.py
confixer/accessor.py
confixer/cli.py
confixer/loader.py
confixer/merge.py
confixer/schema.py
confixer/sources/base.py
confixer/sources/env_source.py
confixer/sources/json_source.py
confixer/sources/toml_source.py
confixer/sources/yaml_source.py
confixer-0.1.0.dist-info/METADATA
confixer-0.1.0.dist-info/WHEEL
confixer-0.1.0.dist-info/entry_points.txt
confixer-0.1.0.dist-info/licenses/LICENSE
confixer-0.1.0.dist-info/RECORD
