Metadata-Version: 2.4
Name: confixer
Version: 0.1.0
Summary: A modern configuration manager for Python with layered overrides and CLI.
Project-URL: Homepage, https://github.com/MaanenDev/Confixer
Project-URL: Repository, https://github.com/MaanenDev/Confixer
Project-URL: Issues, https://github.com/MaanenDev/Confixer/issues
Author-email: MaanenDev <semvanmaanendev@proton.me>
License: MIT
License-File: LICENSE
Keywords: config,configuration,env,json,pydantic,toml,yaml
Classifier: Development Status :: 4 - Beta
Classifier: Intended Audience :: Developers
Classifier: License :: OSI Approved :: MIT License
Classifier: Programming Language :: Python :: 3
Classifier: Programming Language :: Python :: 3.11
Classifier: Programming Language :: Python :: 3.12
Classifier: Topic :: Software Development :: Libraries :: Python Modules
Classifier: Topic :: System :: Systems Administration
Requires-Python: >=3.11.0
Requires-Dist: python-dotenv>=1.0.0
Requires-Dist: pyyaml>=6.0
Requires-Dist: tomli>=2.0.0
Requires-Dist: typer[all]>=0.9.0
Provides-Extra: dev
Requires-Dist: black>=23.0.0; extra == 'dev'
Requires-Dist: pre-commit>=3.0.0; extra == 'dev'
Requires-Dist: pytest-cov>=4.0.0; extra == 'dev'
Requires-Dist: pytest>=7.0.0; extra == 'dev'
Requires-Dist: ruff>=0.1.0; extra == 'dev'
Provides-Extra: validation
Requires-Dist: pydantic>=2.0.0; extra == 'validation'
